hush/__init__.py
hush/_cli.py
hush/_core.py
hush/py.typed
hush/plugin/__init__.py
hush/plugin/_core.py
hush/plugin/_hooks.py
hush/plugin/_specs.py
hush/plugin/_builtin/__init__.py
hush/plugin/_builtin/_core.py
hush/plugin/_builtin/envvars.py
hush/plugin/_builtin/pass_store.py
python_hush-0.3.1.data/scripts/README.md
python_hush-0.3.1.dist-info/METADATA
python_hush-0.3.1.dist-info/WHEEL
python_hush-0.3.1.dist-info/entry_points.txt
python_hush-0.3.1.dist-info/top_level.txt
python_hush-0.3.1.dist-info/RECORD
