Metadata-Version: 2.1
Name: python-hush
Version: 0.3.1
Summary: A Python library that helps manage secrets using tools specified by plugin hooks.
Home-page: https://github.com/bbugyi200/hush
Author: Bryan M Bugyi
Author-email: bryanbugyi34@gmail.com
License: MIT license
Platform: UNKNOWN
Classifier: Development Status :: 3 - Alpha
Classifier: Intended Audience :: Developers
Classifier: License :: OSI Approved :: MIT License
Classifier: Natural Language :: English
Classifier: Programming Language :: Python :: 3
Classifier: Programming Language :: Python :: 3.7
Classifier: Programming Language :: Python :: 3.8
Classifier: Programming Language :: Python :: 3.9
Requires-Python: >=3.7
Requires-Dist: bugyi.lib (~=0.6.1)
Requires-Dist: pluggy (~=1.0)
Requires-Dist: pydantic
Requires-Dist: pylogutils (~=0.1.4)
Requires-Dist: python-clap (~=0.2.2)
